rds_encryptor/__init__.py
rds_encryptor/cli.py
rds_encryptor/db_manager.py
rds_encryptor/encryption_pipeline.py
rds_encryptor/utils.py
rds_encryptor/dms/__init__.py
rds_encryptor/dms/endpoints.py
rds_encryptor/dms/enums.py
rds_encryptor/dms/migration_task.py
rds_encryptor/dms/replication_instance.py
rds_encryptor/dms/task_manager.py
rds_encryptor/rds/__init__.py
rds_encryptor/rds/instance.py
rds_encryptor/rds/parameter_group.py
rds_encryptor/rds/snapshot.py
rds_encryptor-1.0.2.dist-info/licenses/LICENSE
rds_encryptor-1.0.2.dist-info/METADATA
rds_encryptor-1.0.2.dist-info/WHEEL
rds_encryptor-1.0.2.dist-info/entry_points.txt
rds_encryptor-1.0.2.dist-info/top_level.txt
rds_encryptor-1.0.2.dist-info/RECORD
