Metadata-Version: 2.4
Name: rds-encryptor
Version: 1.0.2
Summary: CLI tool for automating RDS encryption to meet SOC2/CMMC compliance.
Author: iYasha
License:                                  Apache License
Project-URL: Source, https://github.com/iYasha/aws-rds-encryptor
Project-URL: Tracker, https://github.com/iYasha/aws-rds-encryptor/issues
Keywords: aws,rds,encryptor,SOC2,CMMC
Classifier: Intended Audience :: Developers
Classifier: License :: OSI Approved :: Apache Software License
Classifier: Operating System :: OS Independent
Classifier: Programming Language :: Python :: 3
Classifier: Programming Language :: Python :: 3 :: Only
Classifier: Programming Language :: Python :: 3.11
Classifier: Programming Language :: Python :: 3.12
Requires-Python: >=3.11
License-File: LICENSE
Requires-Dist: psycopg2>=2.9.10
Requires-Dist: boto3>=1.37.23
Provides-Extra: docs
Requires-Dist: sphinx>=7; extra == "docs"
Dynamic: license-file
